InquirerPy/__init__.py
InquirerPy/base/__init__.py
InquirerPy/base/complex.py
InquirerPy/base/control.py
InquirerPy/base/list.py
InquirerPy/base/simple.py
InquirerPy/containers/__init__.py
InquirerPy/containers/instruction.py
InquirerPy/containers/message.py
InquirerPy/containers/spinner.py
InquirerPy/containers/validation.py
InquirerPy/enum.py
InquirerPy/exceptions.py
InquirerPy/inquirer.py
InquirerPy/prompts/__init__.py
InquirerPy/prompts/checkbox.py
InquirerPy/prompts/confirm.py
InquirerPy/prompts/expand.py
InquirerPy/prompts/filepath.py
InquirerPy/prompts/fuzzy.py
InquirerPy/prompts/input.py
InquirerPy/prompts/list.py
InquirerPy/prompts/number.py
InquirerPy/prompts/rawlist.py
InquirerPy/prompts/secret.py
InquirerPy/resolver.py
InquirerPy/separator.py
InquirerPy/utils.py
InquirerPy/validator.py
inquirerpy-0.3.3.dist-info/LICENSE
inquirerpy-0.3.3.dist-info/WHEEL
inquirerpy-0.3.3.dist-info/METADATA
inquirerpy-0.3.3.dist-info/RECORD
